xmlstreamer/__init__.py
xmlstreamer-1.1.2.dist-info/licenses/LICENSE
xmlstreamer-1.1.2.dist-info/METADATA
xmlstreamer-1.1.2.dist-info/WHEEL
xmlstreamer-1.1.2.dist-info/top_level.txt
xmlstreamer-1.1.2.dist-info/RECORD
