Metadata-Version: 2.4
Name: xmlstreamer
Version: 1.1.2
Summary: Python library to parse XML data directly from HTTP, HTTPS, or FTP sources without loading the entire file into memory, supporting decompression, encoding detection, tag-based itemization, and optional filtering.
Author-email: "Carlos A. Planchón" <carlosandresplanchonprestes@gmail.com>
License-Expression: MIT
Project-URL: repository, https://github.com/carlosplanchon/xmlstreamer.git
Keywords: xml,streaming,parser,lightweight,http,https,ftp
Classifier: Intended Audience :: Developers
Classifier: Topic :: Software Development :: Libraries
Classifier: Programming Language :: Python :: 3 :: Only
Classifier: Programming Language :: Python :: 3.9
Classifier: Programming Language :: Python :: 3.10
Classifier: Programming Language :: Python :: 3.11
Classifier: Programming Language :: Python :: 3.12
Classifier: Programming Language :: Python :: 3.13
Requires-Python: >=3.9
License-File: LICENSE
Requires-Dist: defusedxml==0.7.1
Requires-Dist: chardet==5.2.0
Requires-Dist: requests==2.28.0
Requires-Dist: attrs==23.2.0
Requires-Dist: attrs-strict==1.0.1
Dynamic: license-file
